README.md
pyproject.toml
flok/__init__.py
flok.egg-info/PKG-INFO
flok.egg-info/SOURCES.txt
flok.egg-info/dependency_links.txt
flok.egg-info/top_level.txt