Metadata-Version: 2.4
Name: flok
Version: 0.1.0
Summary: Coming soon.
Author-email: Marius Maryniak <marius.maryniak@w-hs.de>
Maintainer-email: Marius Maryniak <marius.maryniak@w-hs.de>
